MANIFEST.in
README.md
setup.py
allgo/__init__.py
allgo.egg-info/PKG-INFO
allgo.egg-info/SOURCES.txt
allgo.egg-info/dependency_links.txt
allgo.egg-info/top_level.txt