Metadata-Version: 1.1
Name: allgo
Version: 0.1.6
Summary: AllGo client module
Home-page: https://gitlab.inria.fr/allgo/client
Author: Sebastien Campion
Author-email: sebastien.campion@inria.fr
License: AGPL
Platform: UNKNOWN
Classifier: Programming Language :: Python
Classifier: Development Status :: 1 - Planning
Classifier: License :: OSI Approved
Classifier: Natural Language :: French
Classifier: Operating System :: OS Independent
Classifier: Programming Language :: Python :: 2.7
Classifier: Topic :: Communications
